{
  "caption": "Authorization Information",
  "description": "This object provides details such as authorization outcome, associated policies related to activity/event. Defined by D3FEND <a target='_blank' href='https://d3fend.mitre.org/dao/artifact/d3f:Authorization/'>d3f:Authorization</a>.",
  "extends": "object",
  "name": "authorization",
  "attributes": {
    "decision": {
      "description": "Authorization Result/outcome, e.g. allowed, denied",
      "requirement": "optional"
    },
    "policy": {
      "requirement": "optional",
      "description": "Details about the Identity/Access management policies that are applicable."
    }
  }
}